pdfmergetk/__init__.py
pdfmergetk/__main__.py
pdfmergetk/about.py
pdfmergetk/configmanager.py
pdfmergetk/dataclass.py
pdfmergetk/gui.py
pdfmergetk/icons/down.png
pdfmergetk/icons/left.png
pdfmergetk/icons/right.png
pdfmergetk/icons/trash.png
pdfmergetk/icons/up.png
pdfmergetk/iconspath.py
pdfmergetk/installer.py
pdfmergetk/langs.py
pdfmergetk/models.py
pdfmergetk/pathclass.py
pdfmergetk/reader.py
pdfmergetk/reset.py
pdfmergetk/styles.py
pdfmergetk-0.1.5.dist-info/LICENSE
pdfmergetk-0.1.5.dist-info/METADATA
pdfmergetk-0.1.5.dist-info/WHEEL
pdfmergetk-0.1.5.dist-info/entry_points.txt
pdfmergetk-0.1.5.dist-info/RECORD
