Metadata-Version: 2.3
Name: pdfmergetk
Version: 0.1.5
Summary: GUI application to easily merge PDF files with the power of Python.
Home-page: https://github.com/kurotom/PDFMergeTK
License: GPL-3.0-or-later
Keywords: merge pdf,gui,tk,desktop,gui windows,gui linux
Author: kurotom
Author-email: 55354389+kurotom@users.noreply.github.com
Requires-Python: >=3.8,<4.0
Classifier: License :: OSI Approved :: GNU General Public License v3 or later (GPLv3+)
Classifier: Operating System :: OS Independent
Classifier: Programming Language :: Python :: 3
Classifier: Programming Language :: Python :: 3.8
Classifier: Programming Language :: Python :: 3.9
Classifier: Programming Language :: Python :: 3.10
Classifier: Programming Language :: Python :: 3.11
Classifier: Programming Language :: Python :: 3.12
Classifier: Programming Language :: Python :: 3.13
Classifier: Topic :: Desktop Environment
Requires-Dist: Pillow (<=11)
Requires-Dist: platformdirs
Requires-Dist: pymupdf (>=1.21.1,<2.0.0)
Requires-Dist: pypiwin32 ; sys_platform == "win32"
Requires-Dist: pywin32 ; sys_platform == "win32"
Requires-Dist: winshell ; sys_platform == "win32"
Project-URL: Bug Tracker, https://github.com/kurotom/PDFMergeTK/issues
Project-URL: Repository, https://github.com/kurotom/PDFMergeTK
